geodatasets/__init__.py
geodatasets/api.py
geodatasets/data.py
geodatasets/lib.py
geodatasets/json/database.json
geodatasets/tests/__init__.py
geodatasets/tests/test_api.py
geodatasets/tests/test_data.py
geodatasets/tests/test_lib.py
geodatasets-2025.12.1.dist-info/licenses/LICENSE
geodatasets-2025.12.1.dist-info/METADATA
geodatasets-2025.12.1.dist-info/WHEEL
geodatasets-2025.12.1.dist-info/top_level.txt
geodatasets-2025.12.1.dist-info/RECORD
