Metadata-Version: 2.4
Name: geodatasets
Version: 2025.12.1
Summary: Spatial data examples
Author-email: Martin Fleischmann <martin@martinfleischmann.net>
Maintainer: geodatasets contributors
License: BSD 3-Clause
Project-URL: Home, https://github.com/geopandas/geodatasets
Project-URL: Repository, https://github.com/geopandas/geodatasets
Classifier: Intended Audience :: Science/Research
Classifier: License :: OSI Approved :: BSD License
Classifier: Operating System :: OS Independent
Classifier: Programming Language :: Python :: 3
Classifier: Topic :: Scientific/Engineering :: GIS
Requires-Python: >=3.8
License-File: LICENSE
Requires-Dist: pooch
Dynamic: license-file
